trackanimation/__init__.py
trackanimation/animation.py
trackanimation/tracking.py
trackanimation/utils.py
trackanimation-1.0.5.dist-info/LICENSE
trackanimation-1.0.5.dist-info/METADATA
trackanimation-1.0.5.dist-info/WHEEL
trackanimation-1.0.5.dist-info/top_level.txt
trackanimation-1.0.5.dist-info/RECORD
