Metadata-Version: 2.1
Name: trackanimation
Version: 1.0.5
Summary: GPS Track Animation Library
Home-page: https://github.com/JoanMartin/trackanimation
Author: Juan José Martín
Author-email: UNKNOWN
License: Apache License, Version 2.0
Keywords: GPS GPX animation map geospatial geopositioning
Platform: UNKNOWN
Classifier: Development Status :: 5 - Production/Stable
Classifier: License :: OSI Approved :: Apache Software License
Classifier: Intended Audience :: Education
Classifier: Intended Audience :: End Users/Desktop
Classifier: Intended Audience :: Science/Research
Classifier: Topic :: Software Development :: Libraries :: Python Modules
Classifier: Topic :: Multimedia :: Video
Classifier: Programming Language :: Python
Classifier: Programming Language :: Python :: 2
Classifier: Programming Language :: Python :: 2.7
Classifier: Programming Language :: Python :: 3
Classifier: Programming Language :: Python :: 3.5
Requires-Dist: geopy (>=1.16.0)
Requires-Dist: gpxpy (>=1.3.3)
Requires-Dist: pillow (>=5.2.0)
Requires-Dist: matplotlib (>=2.2.3)
Requires-Dist: mplleaflet (==0.0.5)
Requires-Dist: pandas (>=0.23.4)
Requires-Dist: tqdm (>=4.25.0)
Requires-Dist: smopy (==0.0.6)
